isimplify/__init__.py
isimplify/app.py
isimplify/coverletter.pdf
isimplify/dataIngestion.py
isimplify/sentimentAnalysis.py
isimplify/wordCount.py
isimplify-1.2.3.dist-info/METADATA
isimplify-1.2.3.dist-info/WHEEL
isimplify-1.2.3.dist-info/RECORD
