Metadata-Version: 2.1
Name: isimplify
Version: 1.2.3
Summary: simplifies word counting
Author: sunny kumar
Author-email: sunnykumar1516@gmail.com
Requires-Python: >=3.12,<4.0
Classifier: Programming Language :: Python :: 3
Classifier: Programming Language :: Python :: 3.12
Classifier: Programming Language :: Python :: 3.13
Requires-Dist: gradio (>=5.7.1,<6.0.0)
Requires-Dist: huggingface (>=0.0.1,<0.0.2)
Requires-Dist: matplotlib (>=3.9.3,<4.0.0)
Requires-Dist: nltk (>=3.9.1,<4.0.0)
Requires-Dist: pandas (>=2.2.3,<3.0.0)
Requires-Dist: pypdf2 (>=3.0.1,<4.0.0)
Requires-Dist: spacy (>=3.8.2,<4.0.0)
Requires-Dist: torch (>=2.5.1,<3.0.0)
Requires-Dist: transformers (>=4.46.3,<5.0.0)
